brasil.gov.agenda-1.0-py2.7-nspkg.pth
brasil/gov/agenda/testing.py
brasil/gov/agenda/testing.zcml
brasil/gov/agenda/interfaces.py
brasil/gov/agenda/utils.py
brasil/gov/agenda/profiles.zcml
brasil/gov/agenda/logger.py
brasil/gov/agenda/config.py
brasil/gov/agenda/i18n.sh
brasil/gov/agenda/configure.zcml
brasil/gov/agenda/__init__.py
brasil/gov/agenda/setuphandlers.py
brasil/gov/agenda/permissions.zcml
brasil/gov/agenda/behaviors/date.py
brasil/gov/agenda/behaviors/configure.zcml
brasil/gov/agenda/behaviors/__init__.py
brasil/gov/agenda/portlets/calendar.py
brasil/gov/agenda/portlets/busca.pt
brasil/gov/agenda/portlets/busca.py
brasil/gov/agenda/portlets/calendar.pt
brasil/gov/agenda/portlets/configure.zcml
brasil/gov/agenda/portlets/__init__.py
brasil/gov/agenda/caching/configure.zcml
brasil/gov/agenda/caching/__init__.py
brasil/gov/agenda/subscribers/agendadiaria.py
brasil/gov/agenda/subscribers/agenda.py
brasil/gov/agenda/subscribers/__init__.py
brasil/gov/agenda/subscribers/compromisso.py
brasil/gov/agenda/locales/brasil.gov.agenda.pot
brasil/gov/agenda/locales/plone.pot
brasil/gov/agenda/locales/brasil.gov.agenda-manual.pot
brasil/gov/agenda/locales/en/LC_MESSAGES/brasil.gov.agenda.po
brasil/gov/agenda/locales/pt_BR/LC_MESSAGES/brasil.gov.agenda.po
brasil/gov/agenda/static/agenda.css
brasil/gov/agenda/static/icon-file-agenda.png
brasil/gov/agenda/static/icon-clock.png
brasil/gov/agenda/static/agenda-print.css
brasil/gov/agenda/static/icon-horarios.png
brasil/gov/agenda/static/agenda_icon.png
brasil/gov/agenda/static/icon-search-agenda.png
brasil/gov/agenda/static/compromisso_icon.png
brasil/gov/agenda/Extensions/Install.py
brasil/gov/agenda/Extensions/__init__.py
brasil/gov/agenda/tests/test_compromisso.py
brasil/gov/agenda/tests/test_behavior.py
brasil/gov/agenda/tests/keywords.robot
brasil/gov/agenda/tests/brasil.jpg
brasil/gov/agenda/tests/test_portlet_calendar.py
brasil/gov/agenda/tests/test_agendadiaria.robot
brasil.gov.agenda-1.0.dist-info/top_level.txt
brasil.gov.agenda-1.0.dist-info/WHEEL
brasil.gov.agenda-1.0.dist-info/entry_points.txt
brasil.gov.agenda-1.0.dist-info/metadata.json
brasil.gov.agenda-1.0.dist-info/DESCRIPTION.rst
brasil.gov.agenda-1.0.dist-info/METADATA
brasil.gov.agenda-1.0.dist-info/namespace_packages.txt
brasil.gov.agenda-1.0.dist-info/RECORD
