Metadata-Version: 2.0
Name: brasil.gov.agenda
Version: 1.0
Summary: Agenda de membros do Governo Brasileiro
Home-page: https://github.com/plonegovbr/brasil.gov.agenda
Author: PloneGovBr
Author-email: gov@plone.org.br
License: GPLv2
Keywords: plonegovbr agenda brasil plone dexterity
Platform: UNKNOWN
Classifier: Development Status :: 5 - Production/Stable
Classifier: Environment :: Web Environment
Classifier: Framework :: Plone
Classifier: Framework :: Plone :: 4.3
Classifier: Intended Audience :: System Administrators
Classifier: License :: OSI Approved :: GNU General Public License v2 (GPLv2)
Classifier: Operating System :: OS Independent
Classifier: Programming Language :: Python
Classifier: Programming Language :: Python :: 2.7
Classifier: Topic :: Software Development :: Libraries :: Python Modules
Requires-Dist: brasil.gov.tiles
Requires-Dist: collective.portlet.calendar
Requires-Dist: plone.api
Requires-Dist: plone.app.content
Requires-Dist: plone.app.contenttypes (<1.1a1)
Requires-Dist: plone.app.dexterity[grok]
Requires-Dist: plone.app.portlets
Requires-Dist: plone.app.referenceablebehavior
Requires-Dist: plone.app.upgrade
Requires-Dist: plone.app.versioningbehavior
Requires-Dist: plone.app.vocabularies
Requires-Dist: plone.behavior
Requires-Dist: plone.dexterity (<2.2.4)
Requires-Dist: plone.directives.form
Requires-Dist: plone.portlets
Requires-Dist: plone.supermodel (>=1.2.3)
Requires-Dist: plone.uuid
Requires-Dist: Products.CMFCore
Requires-Dist: Products.CMFPlone (>=4.3)
Requires-Dist: Products.GenericSetup
Requires-Dist: setuptools
Requires-Dist: zope.component
Requires-Dist: zope.interface
Requires-Dist: zope.schema
Provides-Extra: test
Requires-Dist: plone.app.robotframework; extra == 'test'
Requires-Dist: plone.app.testing[robot] (>=4.2.2); extra == 'test'
Requires-Dist: plone.browserlayer; extra == 'test'
Requires-Dist: plone.testing; extra == 'test'
